RaspyGeo/__init__.py
RaspyGeo/display.py
RaspyGeo/geofun.py
RaspyGeo/hecgeo.py
RaspyGeo/iterate.py
RaspyGeo/parse_geo.py
RaspyGeo/testing.py
RaspyGeo/write_geo.py
RaspyGeo-1.0.1.dist-info/LICENSE
RaspyGeo-1.0.1.dist-info/METADATA
RaspyGeo-1.0.1.dist-info/WHEEL
RaspyGeo-1.0.1.dist-info/top_level.txt
RaspyGeo-1.0.1.dist-info/RECORD
