Metadata-Version: 2.1
Name: RaspyGeo
Version: 1.0.1
Summary: Automated geometry scenario runner (loosely analogous to the Geometry Editor tool) for HEC-RAS
Home-page: https://github.com/quantum-dan/RaspyGeo
Author: Daniel Philippus
Author-email: daniel@dphilippus.com
Project-URL: Bug Tracker, https://github.com/quantum-dan/RaspyGeo/issues
Classifier: Programming Language :: Python :: 3
Classifier: License :: OSI Approved :: GNU General Public License v3 (GPLv3)
Classifier: Operating System :: Microsoft :: Windows
Requires-Python: >=3.6
License-File: LICENSE
Requires-Dist: raspy-auto (>=1.1.0)
